pyminio/__init__.py
pyminio/exceptions.py
pyminio/main.py
pyminio/py.typed
pyminio/structures.py
pyminio-0.3.1.dist-info/LICENSE
pyminio-0.3.1.dist-info/METADATA
pyminio-0.3.1.dist-info/WHEEL
pyminio-0.3.1.dist-info/RECORD
