Metadata-Version: 2.1
Name: pyminio
Version: 0.3.1
Summary: Python client for Minio
License: MIT
Author: Michael Tugendhaft
Author-email: tugmica@gmail.com
Requires-Python: >=3.8.1,<4.0.0
Classifier: License :: OSI Approved :: MIT License
Classifier: Programming Language :: Python :: 3
Classifier: Programming Language :: Python :: 3.9
Classifier: Programming Language :: Python :: 3.10
Classifier: Programming Language :: Python :: 3.11
Classifier: Programming Language :: Python :: 3.12
Requires-Dist: minio (>=7.2.7)
